dtipod/__main__.py
dtipod/cli.py
dtipod/sql.py
dtipod-0.3.1.dist-info/licenses/COPYING
dtipod-0.3.1.dist-info/METADATA
dtipod-0.3.1.dist-info/WHEEL
dtipod-0.3.1.dist-info/entry_points.txt
dtipod-0.3.1.dist-info/top_level.txt
dtipod-0.3.1.dist-info/RECORD
