Metadata-Version: 2.4
Name: dtipod
Version: 0.3.1
Summary: Podcatcher do_the_internet.sh-style
Home-page: https://git.sr.ht/~mbuechse/dtipod
Author: Matthias Büchse
Author-email: matthias@buech.se
License: GPL-3.0-or-later
Keywords: podcast commandline terminal console podcatcher
Classifier: Development Status :: 3 - Alpha
Classifier: Environment :: Console
Classifier: Intended Audience :: End Users/Desktop
Classifier: Operating System :: POSIX :: Linux
Classifier: Programming Language :: Python :: 3
Classifier: Programming Language :: Python :: 3.10
Classifier: Topic :: Terminals
Requires-Python: >=3
License-File: COPYING
Requires-Dist: beautifulsoup4==4.13.5
Requires-Dist: click==8.2.1
Requires-Dist: lxml==6.0.1
Requires-Dist: pytz==2025.2
Requires-Dist: soupsieve==2.8
Requires-Dist: typing-extensions==4.15.0
Dynamic: author
Dynamic: author-email
Dynamic: classifier
Dynamic: description
Dynamic: description-content-type
Dynamic: home-page
Dynamic: keywords
Dynamic: license
Dynamic: license-file
Dynamic: requires-dist
Dynamic: requires-python
Dynamic: summary
